ragshu/__init__.py
ragshu/math_utils.py
ragshu-0.1.2.dist-info/LICENSE
ragshu-0.1.2.dist-info/METADATA
ragshu-0.1.2.dist-info/WHEEL
ragshu-0.1.2.dist-info/top_level.txt
ragshu-0.1.2.dist-info/RECORD
