Metadata-Version: 2.1
Name: ragshu
Version: 0.1.2
Summary: My First Python Package
Author: Raghav Shukla
Author-email: raghavshukla2010@gmail.com
License: MIT
Classifier: Programming Language :: Python :: 3
Classifier: License :: OSI Approved :: MIT License
Classifier: Operating System :: OS Independent
Requires-Python: >=3.6
License-File: LICENSE
